thefirstock/__init__.py
thefirstock/exchange_socket.py
thefirstock/exchange_socket_copy.py
thefirstock/thefirstock.py
thefirstock/Variables/__init__.py
thefirstock/Variables/common_imports.py
thefirstock/Variables/enums.py
thefirstock/Variables/error_list.py
thefirstock/Variables/fixedParams.py
thefirstock/commonImports/__init__.py
thefirstock/commonImports/importers.py
thefirstock/loginNProfile/__init__.py
thefirstock/loginNProfile/loginFirstock.py
thefirstock/loginNProfile/logoutFirstock.py
thefirstock/loginNProfile/userDetailsFirstock.py
thefirstock/loginNProfile/loginFunctionality/__init__.py
thefirstock/loginNProfile/loginFunctionality/base.py
thefirstock/loginNProfile/loginFunctionality/execution.py
thefirstock/loginNProfile/loginFunctionality/functions.py
thefirstock/loginNProfile/logoutFunctionality/__init__.py
thefirstock/loginNProfile/logoutFunctionality/base.py
thefirstock/loginNProfile/logoutFunctionality/execution.py
thefirstock/loginNProfile/logoutFunctionality/functions.py
thefirstock/loginNProfile/userDetailsFunctionality/__init__.py
thefirstock/loginNProfile/userDetailsFunctionality/base.py
thefirstock/loginNProfile/userDetailsFunctionality/execution.py
thefirstock/loginNProfile/userDetailsFunctionality/functions.py
thefirstock/lookUpTable/__init__.py
thefirstock/lookUpTable/lookUpTableCreation.py
thefirstock/lookUpTable/lookUpVariables.py
thefirstock/lookUpTable/private_enums.py
thefirstock/marketConnect/__init__.py
thefirstock/marketConnect/getIndexListFirstock.py
thefirstock/marketConnect/getMultiQuoteFirstock.py
thefirstock/marketConnect/getMultiQuoteLTPFirstock.py
thefirstock/marketConnect/getOptionChainFirstock.py
thefirstock/marketConnect/getQuoteLTPFirstock.py
thefirstock/marketConnect/getQuotesFirstock.py
thefirstock/marketConnect/getSecurityInfoFirstock.py
thefirstock/marketConnect/optionGreekFirstock.py
thefirstock/marketConnect/searchScripsFirstock.py
thefirstock/marketConnect/spanCalculatorFirstock.py
thefirstock-4.1.0.dist-info/LICENSE
thefirstock-4.1.0.dist-info/METADATA
thefirstock-4.1.0.dist-info/WHEEL
thefirstock-4.1.0.dist-info/top_level.txt
thefirstock-4.1.0.dist-info/RECORD
