Metadata-Version: 2.1
Name: thefirstock
Version: 4.1.0
Author: Firstock
Author-email: technology@thefirstock.com
Classifier: Programming Language :: Python :: 3
Classifier: Operating System :: OS Independent
Classifier: Intended Audience :: Developers
Classifier: License :: OSI Approved :: MIT License
Classifier: Programming Language :: Python :: 3.11
Classifier: Topic :: Software Development :: Libraries :: Python Modules
Requires-Python: >=3.9
License-File: LICENSE
Requires-Dist: requests
Requires-Dist: websockets
Requires-Dist: asyncio
